MANIFEST.in
README.txt
codi.py
setup.py
codi.egg-info/PKG-INFO
codi.egg-info/SOURCES.txt
codi.egg-info/dependency_links.txt
codi.egg-info/top_level.txt
docs/build/html/genindex.html
docs/build/html/index.html
docs/build/html/installation.html
docs/build/html/py-modindex.html
docs/build/html/quick-guide.html
docs/build/html/reference.html
docs/build/html/search.html
docs/source/index.rst
docs/source/installation.rst
docs/source/quick-guide.rst
docs/source/reference.rst