Metadata-Version: 1.1
Name: codi
Version: 1.0.2
Summary: Multiple configuration directories for your program.
Home-page: https://github.com/alghafli/codi
Author: Mohammad Alghafli
Author-email: thebsom@gmail.com
License: UNKNOWN
Keywords: multiple,configuration
Platform: UNKNOWN
Classifier: Development Status :: 4 - Beta
Classifier: Intended Audience :: Developers
Classifier: License :: OSI Approved :: GNU General Public License v3 (GPLv3)
Classifier: Programming Language :: Python :: 3.5
